mathematic_yanwar
